pubwords/__init__.py
pubwords/words.py
pubwords/words.txt
pubwords-1.0.7.dist-info/LICENSE
pubwords-1.0.7.dist-info/METADATA
pubwords-1.0.7.dist-info/WHEEL
pubwords-1.0.7.dist-info/top_level.txt
pubwords-1.0.7.dist-info/RECORD
