Metadata-Version: 2.1
Name: pubwords
Version: 1.0.7
Summary: 19,000 unique words from all publically available PubMed abstracts for use in NLP and spell-checking.
Home-page: https://github.com/Ferrariic/pubwords
Author: Ferrariic
Author-email: ferrariictweet@example.com
License: UNKNOWN
Project-URL: Bug Tracker, https://github.com/Ferrariic/pubwords/issues
Platform: UNKNOWN
Classifier: Programming Language :: Python :: 3
Classifier: License :: OSI Approved :: MIT License
Classifier: Operating System :: OS Independent
Requires-Python: >=3.6
License-File: LICENSE
